jd/__init__.py
jd/api/__init__.py
jd/api/base.py
jd/api/rest/ComEpiBranchOpenApiReadBranchDetailRequest.py
jd/api/rest/ComEpiBranchOpenApiReadBranchListRequest.py
jd/api/rest/ComEpiBranchOpenApiWriteBranchCreationRequest.py
jd/api/rest/ComEpiBranchOpenApiWriteUpdateStatusRequest.py
jd/api/rest/ComEpiCouponOpenApiReadCouponDetailRequest.py
jd/api/rest/ComEpiCouponOpenApiReadCouponListRequest.py
jd/api/rest/ComEpiCouponOpenApiWriteCloseCouponRequest.py
jd/api/rest/ComEpiCouponOpenApiWriteCreateCouponRequest.py
jd/api/rest/ComEpiPromoOpenApiReadGetGiftPromoRequest.py
jd/api/rest/ComEpiPromoOpenApiReadGetPromoListForPageRequest.py
jd/api/rest/ComEpiPromoOpenApiReadGetPromoMainSkuRequest.py
jd/api/rest/ComEpiPromoOpenApiReadGetSuitPromoRequest.py
jd/api/rest/ComEpiPromoOpenApiReadGetTotalPricePromoRequest.py
jd/api/rest/ComEpiPromoOpenApiReadGetUnitPromoRequest.py
jd/api/rest/ComEpiPromoOpenApiWriteCreateGiftPromoRequest.py
jd/api/rest/ComEpiPromoOpenApiWriteCreateSuitPromoRequest.py
jd/api/rest/ComEpiPromoOpenApiWriteCreateSumPromoRequest.py
jd/api/rest/ComEpiPromoOpenApiWriteCreateUnitPromoRequest.py
jd/api/rest/ComEpiPromoOpenApiWriteDelPromoRequest.py
jd/api/rest/ComEpiPromoOpenApiWriteResumePromoRequest.py
jd/api/rest/ComEpiPromoOpenApiWriteSuspendPromoRequest.py
jd/api/rest/ComJdAddressInternationalGlscGlscAddressCodingServiceWSGetChildrenRequest.py
jd/api/rest/ComJdAddressInternationalGlscGlscAddressCodingServiceWSParseAddressCodingRequest.py
jd/api/rest/ComJdAdwordApiServiceAdwordSellerApiServiceCreateAdwordForSkuRequest.py
jd/api/rest/ComJdAdwordApiServiceAdwordSellerApiServiceDeleteAdwordsBySkuIdRequest.py
jd/api/rest/ComJdAdwordApiServiceAdwordSellerApiServiceQueryAdwordsBySkuIdRequest.py
jd/api/rest/ComJdEtmsWaybillApiGlscGlscWaybillTraceApiGetTraceInfoByOrderRequest.py
jd/api/rest/ComJdGmsGreatdaneCategoryServiceReadCategoryReadServiceGetCategorysRequest.py
jd/api/rest/ComJdIntlAsmShopAfsApiServiceQueryAllRequest.py
jd_sdk-1.1.1.dist-info/LICENSE.md
jd_sdk-1.1.1.dist-info/METADATA
jd_sdk-1.1.1.dist-info/WHEEL
jd_sdk-1.1.1.dist-info/top_level.txt
jd_sdk-1.1.1.dist-info/RECORD
