Metadata-Version: 2.1
Name: jd-sdk
Version: 1.1.1
Summary: JD Official SDK
Home-page: https://github.com/PsKs/jd-sdk
Author: Pongsakorn
Author-email: pongsakorn.psks@gmail.com
License: LICENSE.md
Platform: UNKNOWN
Classifier: License :: OSI Approved :: MIT License
Classifier: Programming Language :: Python :: 3
Classifier: Programming Language :: Python :: 3.6
Classifier: Programming Language :: Python :: 3.7
Requires-Python: >=3.6
License-File: LICENSE.md
Requires-Dist: rsa
Requires-Dist: psutil
Requires-Dist: apscheduler
Requires-Dist: wincertstore
Requires-Dist: pycryptodome
